rpc_generated_protobufs/__init__.py
rpc_generated_protobufs/adc_pb2.py
rpc_generated_protobufs/dac_pb2.py
rpc_generated_protobufs/din_pb2.py
rpc_generated_protobufs/dout_pb2.py
rpc_generated_protobufs/led_pb2.py
rpc_generated_protobufs/pwm_pb2.py
rpc_generated_protobufs/relay_pb2.py
rpc_generated_protobufs/rpc_pb2.py
rpc_generated_protobufs/tc_pb2.py
edgepi_rpc_protobuf-1.0.28.dist-info/METADATA
edgepi_rpc_protobuf-1.0.28.dist-info/WHEEL
edgepi_rpc_protobuf-1.0.28.dist-info/top_level.txt
edgepi_rpc_protobuf-1.0.28.dist-info/RECORD
