Metadata-Version: 2.1
Name: edgepi-rpc-protobuf
Version: 1.0.28
Summary: Protobuf generated code for EdgePi RPC
Home-page: https://github.com/EdgePi-Cloud/edgepi-rpc-protobuf/tree/main/python_rpc
Author: Isaac James
Author-email: ijames@osensa.com
Classifier: Programming Language :: Python :: 3
Classifier: License :: OSI Approved :: MIT License
Classifier: Operating System :: OS Independent
Requires-Python: >=3.7
